.gitignore
CMakeLists.txt
pyproject.toml
rl_env_example.py
setup.py
.github/workflows/python-publish.yml
.vscode/launch.json
bad/badagent.py
bad/main.py
bad/runner.py
hanabi_learning_environment/CMakeLists.txt
hanabi_learning_environment/__init__.py
hanabi_learning_environment/pyhanabi.cc
hanabi_learning_environment/pyhanabi.h
hanabi_learning_environment/pyhanabi.py
hanabi_learning_environment/rl_env.py
hanabi_learning_environment/agents/__init__.py
hanabi_learning_environment/agents/random_agent.py
hanabi_learning_environment/agents/simple_agent.py
hanabi_learning_environment/agents/rainbow/README.md
hanabi_learning_environment/agents/rainbow/dqn_agent.py
hanabi_learning_environment/agents/rainbow/prioritized_replay_memory.py
hanabi_learning_environment/agents/rainbow/rainbow_agent.py
hanabi_learning_environment/agents/rainbow/replay_memory.py
hanabi_learning_environment/agents/rainbow/run_experiment.py
hanabi_learning_environment/agents/rainbow/train.py
hanabi_learning_environment/agents/rainbow/configs/hanabi_rainbow.gin
hanabi_learning_environment/agents/rainbow/third_party/__init__.py
hanabi_learning_environment/agents/rainbow/third_party/dopamine/LICENSE
hanabi_learning_environment/agents/rainbow/third_party/dopamine/__init__.py
hanabi_learning_environment/agents/rainbow/third_party/dopamine/checkpointer.py
hanabi_learning_environment/agents/rainbow/third_party/dopamine/iteration_statistics.py
hanabi_learning_environment/agents/rainbow/third_party/dopamine/logger.py
hanabi_learning_environment/agents/rainbow/third_party/dopamine/sum_tree.py
hanabi_learning_environment/examples/CMakeLists.txt
hanabi_learning_environment/examples/README.md
hanabi_learning_environment/examples/game_example.cc
hanabi_learning_environment/examples/game_example.py
hanabi_learning_environment/examples/rl_env_example.py
hanabi_learning_environment/hanabi_lib/CMakeLists.txt
hanabi_learning_environment/hanabi_lib/canonical_encoders.cc
ws2223_group7_hanabi_learning_environment_alexb.egg-info/PKG-INFO
ws2223_group7_hanabi_learning_environment_alexb.egg-info/SOURCES.txt
ws2223_group7_hanabi_learning_environment_alexb.egg-info/dependency_links.txt
ws2223_group7_hanabi_learning_environment_alexb.egg-info/requires.txt
ws2223_group7_hanabi_learning_environment_alexb.egg-info/top_level.txt