Metadata-Version: 2.1
Name: ws2223-group7-hanabi-learning-environment-alexb
Version: 0.0.1
Summary: ws2223-group7 Learning environment for the game of hanabi for alexb.
Home-page: UNKNOWN
Author: ws2223-group7/hanabi-learning-environment
License: UNKNOWN
Platform: UNKNOWN
Classifier: Programming Language :: Python :: 3
Classifier: Operating System :: POSIX :: Linux
Requires-Python: >=3.6
